Metadata-Version: 2.1
Name: bbcu.singleCellBamQueries
Version: 1.0.2
Summary: Queries on bam file of single cell per genome position
Home-page: UNKNOWN
Author: Refael Kohen
Author-email: refael.kohen@weizmann.ac.il
License: UNKNOWN
Platform: UNKNOWN
